quick_queue/__init__.py
quick_queue/quick_queue.py
quick_queue-1.0.7.dist-info/LICENSE
quick_queue-1.0.7.dist-info/METADATA
quick_queue-1.0.7.dist-info/WHEEL
quick_queue-1.0.7.dist-info/top_level.txt
quick_queue-1.0.7.dist-info/RECORD
