Metadata-Version: 2.1
Name: quick-queue
Version: 1.0.7
Summary: Quick Multiprocessing Queue for Python (Wrap of multiprocessing.queue to increase data transfer velocity between processes)
Home-page: https://github.com/Invarato/sort_in_disk_project
Author: Ramon Invarato Menendez
Author-email: r.invarato@gmail.com
License: UNKNOWN
Platform: UNKNOWN
Classifier: Programming Language :: Python :: 3
Classifier: License :: OSI Approved :: MIT License
Classifier: Operating System :: OS Independent
Requires-Python: >=3.0
